enigma_driver.py
enigma/__init__.py
enigma/config.ini
enigma/enigma_exception.py
enigma/enigma_machine.py
enigma/model.ini
enigma/plugboard.py
enigma/reflect.py
enigma/rotor.py
enigma_cli-1.0.0.dist-info/DESCRIPTION.rst
enigma_cli-1.0.0.dist-info/METADATA
enigma_cli-1.0.0.dist-info/RECORD
enigma_cli-1.0.0.dist-info/WHEEL
enigma_cli-1.0.0.dist-info/entry_points.txt
enigma_cli-1.0.0.dist-info/metadata.json
enigma_cli-1.0.0.dist-info/top_level.txt
