Metadata-Version: 2.0
Name: enigma-cli
Version: 1.0.0
Summary: German Cipher Machine Command-Line Tool
Home-page: UNKNOWN
Author: cjengdahl
Author-email: cjengdahl@gmail.com
License: MIT
Platform: UNKNOWN
Classifier: Development Status :: 5 - Production/Stable
Classifier: Intended Audience :: Other Audience
Classifier: License :: OSI Approved :: MIT License
Classifier: Programming Language :: Python :: 3.4
Classifier: Programming Language :: Python :: 3.5
Requires-Dist: Click
